pip_services4_config/__init__.py
pip_services4_config/auth/CredentialParams.py
pip_services4_config/auth/CredentialResolver.py
pip_services4_config/auth/DefaultCredentialStoreFactory.py
pip_services4_config/auth/ICredentialStore.py
pip_services4_config/auth/MemoryCredentialStore.py
pip_services4_config/auth/__init__.py
pip_services4_config/build/DefaultConfigFactory.py
pip_services4_config/build/__init__.py
pip_services4_config/config/ConfigReader.py
pip_services4_config/config/DefaultConfigReaderFactory.py
pip_services4_config/config/FileConfigReader.py
pip_services4_config/config/IConfigReader.py
pip_services4_config/config/JsonConfigReader.py
pip_services4_config/config/MemoryConfigReader.py
pip_services4_config/config/YamlConfigReader.py
pip_services4_config/config/__init__.py
pip_services4_config/connect/CompositeConnectionResolver.py
pip_services4_config/connect/ConnectionParams.py
pip_services4_config/connect/ConnectionResolver.py
pip_services4_config/connect/ConnectionUtils.py
pip_services4_config/connect/DefaultDiscoveryFactory.py
pip_services4_config/connect/IDiscovery.py
pip_services4_config/connect/MemoryDiscovery.py
pip_services4_config/connect/__init__.py
pip_services4_config-0.0.3.dist-info/LICENSE
pip_services4_config-0.0.3.dist-info/METADATA
pip_services4_config-0.0.3.dist-info/WHEEL
pip_services4_config-0.0.3.dist-info/top_level.txt
pip_services4_config-0.0.3.dist-info/zip-safe
pip_services4_config-0.0.3.dist-info/RECORD
